pyhbr/__init__.py
pyhbr/common.py
pyhbr/analysis/__init__.py
pyhbr/analysis/acs.py
pyhbr/analysis/arc_hbr.py
pyhbr/analysis/calibration.py
pyhbr/analysis/describe.py
pyhbr/analysis/dim_reduce.py
pyhbr/analysis/fit.py
pyhbr/analysis/model.py
pyhbr/analysis/patient_viewer.py
pyhbr/analysis/roc.py
pyhbr/analysis/stability.py
pyhbr/clinical_codes/__init__.py
pyhbr/clinical_codes/counting.py
pyhbr/clinical_codes/codes_editor/__init__.py
pyhbr/clinical_codes/codes_editor/codes_editor.py
pyhbr/clinical_codes/files/icd10.yaml
pyhbr/clinical_codes/files/icd10_arc_hbr.yaml
pyhbr/clinical_codes/files/icd10_blank.yaml
pyhbr/clinical_codes/files/icd10_dim_reduce.yaml
pyhbr/clinical_codes/files/icd10_test.yaml
pyhbr/clinical_codes/files/opcs4_arc_hbr.yaml
pyhbr/clinical_codes/files/opcs4_blank.yaml
pyhbr/clinical_codes/files/opcs4_dim_reduce.yaml
pyhbr/data_source/__init__.py
pyhbr/data_source/hic.py
pyhbr/data_source/hic_covid.py
pyhbr/data_source/hic_icb.py
pyhbr/data_source/icb.py
pyhbr/middle/__init__.py
pyhbr/middle/from_hic.py
pyhbr/middle/from_icb.py
pyhbr/tools/__init__.py
pyhbr/tools/fetch_data.py
pyhbr/tools/generate_report.py
pyhbr/tools/get_csv.py
pyhbr/tools/make_results.py
pyhbr/tools/plot_describe.py
pyhbr/tools/run_model.py
pyhbr-0.0.9.dist-info/METADATA
pyhbr-0.0.9.dist-info/WHEEL
pyhbr-0.0.9.dist-info/entry_points.txt
pyhbr-0.0.9.dist-info/licenses/LICENSE
pyhbr-0.0.9.dist-info/RECORD
