Metadata-Version: 2.3
Name: pyhbr
Version: 0.0.9
Summary: Tools for bleeding/ischaemia risk estimation in PCI patients
Project-URL: Homepage, https://github.com/jrs0/hbr_uhbw
Author-email: John Scott <john.scott@uhbw.nhs.uk>
License-File: LICENSE
Classifier: License :: OSI Approved :: GNU General Public License v3 (GPLv3)
Classifier: Operating System :: OS Independent
Classifier: Programming Language :: Python :: 3
Requires-Python: >=3.9
Requires-Dist: gitpython
Requires-Dist: loguru
Requires-Dist: matplotlib
Requires-Dist: nbclient
Requires-Dist: nbformat
Requires-Dist: pandas
Requires-Dist: pyodbc
Requires-Dist: pyqt6
Requires-Dist: pyserde[yaml]
Requires-Dist: scikit-learn
Requires-Dist: scikit-survival
Requires-Dist: seaborn
Requires-Dist: sqlalchemy
Requires-Dist: tabulate
Requires-Dist: xgboost
